{"_internal":{"pubDateTime":"2020-01-31 23:27:52.857 EST","igorPath":"S3,1580531271237,1580531272415|router,1580531272415,1580531272419|domUpdater,1580531272529,1580531272662|feedProducer,1580531272830,1580531272859","xslt":"NBA/xsl/game/playbyplay/marty_lead_tracker.xsl","xsltForceRecompile":"true","xsltInCache":"false","xsltCompileTimeMillis":"15","xsltTransformTimeMillis":"4","consolidatedDomKey":"prod__transform__marty_lead_tracker__3777052161699","endToEndTimeMillis":"1622"},"plays":[{"clock":"11:46","leadTeamId":"1610612749","points":"5"},{"clock":"11:21","leadTeamId":"1610612749","points":"6"},{"clock":"09:43","leadTeamId":"1610612749","points":"7"},{"clock":"09:35","leadTeamId":"1610612749","points":"5"},{"clock":"08:58","leadTeamId":"1610612749","points":"3"},{"clock":"08:58","leadTeamId":"1610612749","points":"2"},{"clock":"08:25","leadTeamId":"1610612749","points":"1"},{"clock":"08:25","leadTeamId":"","points":"0"},{"clock":"08:07","leadTeamId":"1610612749","points":"2"},{"clock":"07:48","leadTeamId":"1610612749","points":"4"},{"clock":"07:29","leadTeamId":"1610612749","points":"1"},{"clock":"07:13","leadTeamId":"1610612749","points":"3"},{"clock":"06:20","leadTeamId":"","points":"0"},{"clock":"06:10","leadTeamId":"1610612749","points":"2"},{"clock":"05:56","leadTeamId":"1610612743","points":"1"},{"clock":"05:32","leadTeamId":"1610612743","points":"3"},{"clock":"05:12","leadTeamId":"1610612743","points":"1"},{"clock":"04:59","leadTeamId":"1610612743","points":"4"},{"clock":"04:40","leadTeamId":"1610612743","points":"1"},{"clock":"04:19","leadTeamId":"1610612743","points":"3"},{"clock":"03:57","leadTeamId":"1610612743","points":"6"},{"clock":"03:30","leadTeamId":"1610612743","points":"5"},{"clock":"03:01","leadTeamId":"1610612743","points":"7"},{"clock":"02:43","leadTeamId":"1610612743","points":"10"},{"clock":"02:22","leadTeamId":"1610612743","points":"8"},{"clock":"02:06","leadTeamId":"1610612743","points":"7"},{"clock":"01:22","leadTeamId":"1610612743","points":"9"},{"clock":"01:10","leadTeamId":"1610612743","points":"6"},{"clock":"00:27.5","leadTeamId":"1610612743","points":"8"},{"clock":"00:11.2","leadTeamId":"1610612743","points":"7"},{"clock":"00:11.2","leadTeamId":"1610612743","points":"6"},{"clock":"00:01.9","leadTeamId":"1610612743","points":"9"}]}