{"_internal":{"pubDateTime":"2020-02-01 07:34:14.105 EST","igorPath":"S3,1580560449109,1580560452941|router,1580560452941,1580560452947|domUpdater,1580560453073,1580560453685|feedProducer,1580560453777,1580560454466","routeName":"ap_recap_article","routeValue":"S3::ap_recap_20200131_0021900726.xml","xslt":"NBA/xsl/game/boxscore/marty_boxscore.xsl","xsltForceRecompile":"true","xsltInCache":"false","xsltCompileTimeMillis":"282","xsltTransformTimeMillis":"373","consolidatedDomKey":"prod__transform__marty_boxscore__3016613350030","endToEndTimeMillis":"5357"},"basicGameData":{"seasonStageId":2,"seasonYear":"2019","leagueName":"standard","gameId":"0021900726","arena":{"name":"Staples Center","isDomestic":true,"city":"Los Angeles","stateAbbr":"CA","country":"USA"},"isGameActivated":false,"statusNum":3,"extendedStatusNum":0,"startTimeEastern":"10:30 PM ET","startTimeUTC":"2020-02-01T03:30:00.000Z","endTimeUTC":"2020-02-01T06:21:00.000Z","startDateEastern":"20200131","homeStartDate":"20200131","homeStartTime":"1930","visitorStartDate":"20200131","visitorStartTime":"1930","gameUrlCode":"20200131/PORLAL","clock":"","isBuzzerBeater":false,"isPreviewArticleAvail":true,"isRecapArticleAvail":true,"nugget":{"text":"Lillard: 48 points, 9 rebounds, 10 assists"},"attendance":"18997","tickets":{"mobileApp":"https://a.data.nba.com/tickets/single/2019/0021900726/APP_TIX","desktopWeb":"https://a.data.nba.com/tickets/single/2019/0021900726/TEAM_SCH","mobileWeb":"https://a.data.nba.com/tickets/single/2019/0021900726/WEB_MWEB","leagGameInfo":"https://a.data.nba.com/tickets/single/2019/0021900726/LEAG_GAMEINFO","leagTix":"https://a.data.nba.com/tickets/single/2019/0021900726/LEAG_TIX"},"hasGameBookPdf":true,"isStartTimeTBD":false,"gameDuration":{"hours":"2","minutes":"23"},"period":{"current":4,"type":0,"maxRegular":4,"isHalftime":false,"isEndOfPeriod":false},"vTeam":{"teamId":"1610612757","triCode":"POR","win":"22","loss":"27","seriesWin":"1","seriesLoss":"2","score":"127","linescore":[{"score":"38"},{"score":"22"},{"score":"43"},{"score":"24"}]},"hTeam":{"teamId":"1610612747","triCode":"LAL","win":"36","loss":"11","seriesWin":"2","seriesLoss":"1","score":"119","linescore":[{"score":"36"},{"score":"26"},{"score":"34"},{"score":"23"}]},"watch":{"broadcast":{"broadcasters":{"national":[{"shortName":"ESPN","longName":"ESPN"}],"canadian":[{"shortName":"TSN1","longName":"TSN1"}],"vTeam":[{"shortName":"NBCSNW","longName":"NBC SPORTS NORTHWEST"}],"hTeam":[{"shortName":"SPECSN","longName":"Spectrum SportsNet"}],"spanish_hTeam":[],"spanish_vTeam":[],"spanish_national":[]},"video":{"regionalBlackoutCodes":"torr_lalr_porr","canPurchase":true,"isLeaguePass":true,"isNationalBlackout":false,"isTNTOT":false,"isVR":false,"tntotIsOnAir":false,"isNextVR":false,"isNBAOnTNTVR":false,"isMagicLeap":false,"isOculusVenues":false,"streams":[{"streamType":"vTeam","isOnAir":false,"doesArchiveExist":true,"isArchiveAvailToWatch":true,"streamId":"100219007261220","duration":0},{"streamType":"hTeam","isOnAir":false,"doesArchiveExist":false,"isArchiveAvailToWatch":false,"streamId":"","duration":0},{"streamType":"espanol_vTeam","isOnAir":false,"doesArchiveExist":false,"isArchiveAvailToWatch":false,"streamId":"","duration":0},{"streamType":"espanol_hTeam","isOnAir":false,"doesArchiveExist":true,"isArchiveAvailToWatch":true,"streamId":"100219007261420","duration":0},{"streamType":"espanol_natl","isOnAir":false,"doesArchiveExist":false,"isArchiveAvailToWatch":false,"streamId":"","duration":0},{"streamType":"mobile","isOnAir":false,"doesArchiveExist":true,"isArchiveAvailToWatch":true,"streamId":"100219007261320","duration":0},{"streamType":"condensed","isOnAir":false,"doesArchiveExist":true,"isArchiveAvailToWatch":true,"streamId":"100219007261030","duration":0},{"streamType":"alt","isOnAir":false,"doesArchiveExist":false,"isArchiveAvailToWatch":false,"streamId":"","duration":0}],"deepLink":[{"broadcaster":"ESPN","regionalMarketCodes":"","iosApp":"http://www.espn.com/watch?id=3581008","androidApp":"http://www.espn.com/watch?id=3581008","desktopWeb":"http://www.espn.com/watch?id=3581008","mobileWeb":"http://www.espn.com/watch?id=3581008"}]},"audio":{"national":{"streams":[{"language":"English","isOnAir":false,"streamId":""},{"language":"Spanish","isOnAir":false,"streamId":""}],"broadcasters":[]},"vTeam":{"streams":[{"language":"English","isOnAir":false,"streamId":""},{"language":"Spanish","isOnAir":false,"streamId":""}],"broadcasters":[{"shortName":"Rip City Radio 620","longName":"Rip City Radio 620"}]},"hTeam":{"streams":[{"language":"English","isOnAir":false,"streamId":""},{"language":"Spanish","isOnAir":false,"streamId":""}],"broadcasters":[{"shortName":"710 AM ESPN / 1330 AM ESPN DEPORTES","longName":"710 AM ESPN / 1330 AM ESPN DEPORTES"}]}}}},"officials":{"formatted":[{"firstNameLastName":"Tom Washington"},{"firstNameLastName":"Derrick Collins"},{"firstNameLastName":"Matt Boland"}]}},"previousMatchup":{"gameId":"0021900484","gameDate":"20191228"},"stats":{"timesTied":"15","leadChanges":"17","vTeam":{"fastBreakPoints":"24","pointsInPaint":"60","biggestLead":"12","secondChancePoints":"15","pointsOffTurnovers":"17","longestRun":"9","totals":{"points":"127","fgm":"49","fga":"97","fgp":"50.5","ftm":"16","fta":"21","ftp":"76.2","tpm":"13","tpa":"36","tpp":"36.1","offReb":"6","defReb":"35","totReb":"41","assists":"25","pFouls":"22","steals":"9","turnovers":"5","blocks":"8","plusMinus":"8","min":"240:00","short_timeout_remaining":"0","full_timeout_remaining":"2","team_fouls":"22"},"leaders":{"points":{"value":"48","players":[{"personId":"203081","firstName":"Damian","lastName":"Lillard"}]},"rebounds":{"value":"13","players":[{"personId":"202355","firstName":"Hassan","lastName":"Whiteside"}]},"assists":{"value":"10","players":[{"personId":"203081","firstName":"Damian","lastName":"Lillard"}]}}},"hTeam":{"fastBreakPoints":"42","pointsInPaint":"60","biggestLead":"6","secondChancePoints":"27","pointsOffTurnovers":"8","longestRun":"9","totals":{"points":"119","fgm":"45","fga":"96","fgp":"46.9","ftm":"18","fta":"28","ftp":"64.3","tpm":"11","tpa":"32","tpp":"34.4","offReb":"18","defReb":"43","totReb":"61","assists":"28","pFouls":"21","steals":"2","turnovers":"17","blocks":"10","plusMinus":"-8","min":"240:00","short_timeout_remaining":"0","full_timeout_remaining":"1","team_fouls":"20"},"leaders":{"points":{"value":"37","players":[{"personId":"203076","firstName":"Anthony","lastName":"Davis"}]},"rebounds":{"value":"15","players":[{"personId":"203076","firstName":"Anthony","lastName":"Davis"},{"personId":"1628398","firstName":"Kyle","lastName":"Kuzma"}]},"assists":{"value":"10","players":[{"personId":"2544","firstName":"LeBron","lastName":"James"}]}}},"activePlayers":[{"personId":"2772","firstName":"Trevor","lastName":"Ariza","jersey":"8","teamId":"1610612757","isOnCourt":true,"points":"2","pos":"SF","position_full":"Small Forward","player_code":"trevor_ariza","min":"39:04","fgm":"1","fga":"5","fgp":"20.0","ftm":"0","fta":"0","ftp":"0.0","tpm":"0","tpa":"2","tpp":"0.0","offReb":"0","defReb":"4","totReb":"4","assists":"3","pFouls":"3","steals":"5","turnovers":"0","blocks":"1","plusMinus":"-5","dnp":"","sortKey":{"name":1,"pos":0,"points":19,"min":3,"fgm":18,"fga":12,"fgp":18,"ftm":23,"fta":23,"ftp":23,"tpm":22,"tpa":12,"tpp":22,"offReb":24,"defReb":9,"totReb":10,"assists":6,"pFouls":6,"steals":1,"turnovers":23,"blocks":8,"plusMinus":20}},{"personId":"1629117","firstName":"Wenyen","lastName":"Gabriel","jersey":"35","teamId":"1610612757","isOnCourt":false,"points":"0","pos":"PF","position_full":"Power Forward","player_code":"wenyen_gabriel","min":"12:40","fgm":"0","fga":"3","fgp":"0.0","ftm":"0","fta":"0","ftp":"0.0","tpm":"0","tpa":"1","tpp":"0.0","offReb":"1","defReb":"0","totReb":"1","assists":"1","pFouls":"6","steals":"0","turnovers":"0","blocks":"1","plusMinus":"5","dnp":"","sortKey":{"name":2,"pos":0,"points":24,"min":17,"fgm":24,"fga":20,"fgp":24,"ftm":24,"fta":24,"ftp":24,"tpm":24,"tpa":18,"tpp":24,"offReb":13,"defReb":24,"totReb":18,"assists":16,"pFouls":1,"steals":24,"turnovers":24,"blocks":9,"plusMinus":8}},{"personId":"202355","firstName":"Hassan","lastName":"Whiteside","jersey":"21","teamId":"1610612757","isOnCourt":true,"points":"30","pos":"C","position_full":"Center","player_code":"hassan_whiteside","min":"33:44","fgm":"13","fga":"14","fgp":"92.9","ftm":"4","fta":"6","ftp":"66.7","tpm":"0","tpa":"0","tpp":"0.0","offReb":"3","defReb":"10","totReb":"13","assists":"2","pFouls":"1","steals":"2","turnovers":"0","blocks":"5","plusMinus":"8","dnp":"","sortKey":{"name":3,"pos":0,"points":3,"min":6,"fgm":3,"fga":5,"fgp":3,"ftm":4,"fta":4,"ftp":8,"tpm":16,"tpa":22,"tpp":16,"offReb":3,"defReb":2,"totReb":3,"assists":10,"pFouls":17,"steals":3,"turnovers":17,"blocks":2,"plusMinus":3}},{"personId":"203468","firstName":"CJ","lastName":"McCollum","jersey":"3","teamId":"1610612757","isOnCourt":true,"points":"19","pos":"SG","position_full":"Shooting Guard","player_code":"cj_mccollum","min":"40:03","fgm":"8","fga":"22","fgp":"36.4","ftm":"1","fta":"2","ftp":"50.0","tpm":"2","tpa":"9","tpp":"22.2","offReb":"1","defReb":"5","totReb":"6","assists":"5","pFouls":"0","steals":"0","turnovers":"0","blocks":"0","plusMinus":"1","dnp":"","sortKey":{"name":4,"pos":0,"points":5,"min":2,"fgm":5,"fga":3,"fgp":13,"ftm":9,"fta":9,"ftp":9,"tpm":5,"tpa":2,"tpp":9,"offReb":7,"defReb":7,"totReb":7,"assists":4,"pFouls":21,"steals":11,"turnovers":15,"blocks":15,"plusMinus":11}},{"personId":"203081","firstName":"Damian","lastName":"Lillard","jersey":"0","teamId":"1610612757","isOnCourt":true,"points":"48","pos":"PG","position_full":"Point Guard","player_code":"damian_lillard","min":"40:16","fgm":"17","fga":"30","fgp":"56.7","ftm":"7","fta":"8","ftp":"87.5","tpm":"7","tpa":"12","tpp":"58.3","offReb":"1","defReb":"8","totReb":"9","assists":"10","pFouls":"1","steals":"2","turnovers":"1","blocks":"0","plusMinus":"12","dnp":"","sortKey":{"name":5,"pos":0,"points":1,"min":1,"fgm":1,"fga":1,"fgp":7,"ftm":1,"fta":2,"ftp":4,"tpm":1,"tpa":1,"tpp":4,"offReb":8,"defReb":4,"totReb":4,"assists":1,"pFouls":15,"steals":2,"turnovers":6,"blocks":16,"plusMinus":1}},{"personId":"1629018","firstName":"Gary","lastName":"Trent Jr.","jersey":"2","teamId":"1610612757","isOnCourt":true,"points":"10","pos":"","position_full":"","player_code":"tmp_gary_trent","min":"22:03","fgm":"4","fga":"9","fgp":"44.4","ftm":"0","fta":"0","ftp":"0.0","tpm":"2","tpa":"5","tpp":"40.0","offReb":"0","defReb":"0","totReb":"0","assists":"1","pFouls":"2","steals":"0","turnovers":"1","blocks":"0","plusMinus":"10","dnp":"","sortKey":{"name":6,"pos":0,"points":8,"min":9,"fgm":7,"fga":7,"fgp":10,"ftm":17,"fta":17,"ftp":17,"tpm":6,"tpa":6,"tpp":6,"offReb":18,"defReb":18,"totReb":21,"assists":13,"pFouls":8,"steals":14,"turnovers":8,"blocks":17,"plusMinus":2}},{"personId":"1629642","firstName":"Nassir","lastName":"Little","jersey":"9","teamId":"1610612757","isOnCourt":false,"points":"8","pos":"","position_full":"","player_code":"nassir_little","min":"11:14","fgm":"3","fga":"5","fgp":"60.0","ftm":"0","fta":"0","ftp":"0.0","tpm":"2","tpa":"4","tpp":"50.0","offReb":"0","defReb":"0","totReb":"0","assists":"0","pFouls":"2","steals":"0","turnovers":"0","blocks":"0","plusMinus":"8","dnp":"","sortKey":{"name":7,"pos":0,"points":10,"min":19,"fgm":12,"fga":11,"fgp":6,"ftm":20,"fta":20,"ftp":20,"tpm":7,"tpa":7,"tpp":5,"offReb":21,"defReb":20,"totReb":22,"assists":23,"pFouls":12,"steals":20,"turnovers":21,"blocks":21,"plusMinus":4}},{"personId":"1629014","firstName":"Anfernee","lastName":"Simons","jersey":"1","teamId":"1610612757","isOnCourt":false,"points":"4","pos":"","position_full":"","player_code":"anfernee_simons","min":"15:34","fgm":"1","fga":"3","fgp":"33.3","ftm":"2","fta":"2","ftp":"100","tpm":"0","tpa":"1","tpp":"0.0","offReb":"0","defReb":"0","totReb":"0","assists":"2","pFouls":"0","steals":"0","turnovers":"0","blocks":"0","plusMinus":"4","dnp":"","sortKey":{"name":8,"pos":0,"points":15,"min":12,"fgm":14,"fga":16,"fgp":14,"ftm":5,"fta":7,"ftp":1,"tpm":12,"tpa":14,"tpp":12,"offReb":15,"defReb":16,"totReb":19,"assists":8,"pFouls":19,"steals":7,"turnovers":12,"blocks":11,"plusMinus":9}},{"personId":"1628403","firstName":"Caleb","lastName":"Swanigan","jersey":"50","teamId":"1610612757","isOnCourt":false,"points":"5","pos":"","position_full":"","player_code":"caleb_swanigan","min":"13:53","fgm":"2","fga":"2","fgp":"100","ftm":"1","fta":"1","ftp":"100","tpm":"0","tpa":"0","tpp":"0.0","offReb":"0","defReb":"6","totReb":"6","assists":"1","pFouls":"4","steals":"0","turnovers":"3","blocks":"0","plusMinus":"2","dnp":"","sortKey":{"name":9,"pos":0,"points":13,"min":16,"fgm":13,"fga":22,"fgp":1,"ftm":8,"fta":13,"ftp":3,"tpm":13,"tpa":19,"tpp":13,"offReb":16,"defReb":5,"totReb":6,"assists":11,"pFouls":3,"steals":9,"turnovers":4,"blocks":13,"plusMinus":10}},{"personId":"1626209","firstName":"Mario","lastName":"Hezonja","jersey":"44","teamId":"1610612757","isOnCourt":false,"points":"1","pos":"","position_full":"","player_code":"mario_hezonja","min":"11:27","fgm":"0","fga":"4","fgp":"0.0","ftm":"1","fta":"2","ftp":"50.0","tpm":"0","tpa":"2","tpp":"0.0","offReb":"0","defReb":"2","totReb":"2","assists":"0","pFouls":"3","steals":"0","turnovers":"0","blocks":"1","plusMinus":"-5","dnp":"","sortKey":{"name":10,"pos":0,"points":20,"min":18,"fgm":23,"fga":14,"fgp":23,"ftm":12,"fta":11,"ftp":11,"tpm":20,"tpa":11,"tpp":20,"offReb":20,"defReb":14,"totReb":15,"assists":22,"pFouls":5,"steals":19,"turnovers":20,"blocks":7,"plusMinus":19}},{"personId":"2546","firstName":"Carmelo","lastName":"Anthony","jersey":"00","teamId":"1610612757","isOnCourt":false,"points":"0","pos":"","position_full":"","player_code":"carmelo_anthony","min":"0:00","fgm":"0","fga":"0","fgp":"0.0","ftm":"0","fta":"0","ftp":"0.0","tpm":"0","tpa":"0","tpp":"0.0","offReb":"0","defReb":"0","totReb":"0","assists":"0","pFouls":"0","steals":"0","turnovers":"0","blocks":"0","plusMinus":"0","dnp":"","sortKey":{"name":11,"pos":0,"points":22,"min":24,"fgm":21,"fga":23,"fgp":21,"ftm":15,"fta":15,"ftp":15,"tpm":14,"tpa":20,"tpp":14,"offReb":17,"defReb":17,"totReb":20,"assists":17,"pFouls":20,"steals":10,"turnovers":14,"blocks":14,"plusMinus":14}},{"personId":"203994","firstName":"Jusuf","lastName":"Nurkic","jersey":"27","teamId":"1610612757","isOnCourt":false,"points":"","pos":"","position_full":"","player_code":"jusuf_nurkic","min":"","fgm":"","fga":"","fgp":"","ftm":"","fta":"","ftp":"","tpm":"","tpa":"","tpp":"","offReb":"","defReb":"","totReb":"","assists":"","pFouls":"","steals":"","turnovers":"","blocks":"","plusMinus":"","dnp":"DND - Injury / Illness","sortKey":{"name":12,"pos":0,"points":25,"min":25,"fgm":25,"fga":25,"fgp":25,"ftm":25,"fta":25,"ftp":25,"tpm":25,"tpa":25,"tpp":25,"offReb":25,"defReb":25,"totReb":25,"assists":25,"pFouls":25,"steals":25,"turnovers":25,"blocks":25,"plusMinus":25}},{"personId":"2544","firstName":"LeBron","lastName":"James","jersey":"23","teamId":"1610612747","isOnCourt":true,"points":"22","pos":"SF","position_full":"Small Forward","player_code":"lebron_james","min":"37:59","fgm":"9","fga":"22","fgp":"40.9","ftm":"1","fta":"4","ftp":"25.0","tpm":"3","tpa":"8","tpp":"37.5","offReb":"2","defReb":"6","totReb":"8","assists":"10","pFouls":"2","steals":"0","turnovers":"5","blocks":"1","plusMinus":"7","dnp":"","sortKey":{"name":41,"pos":0,"points":4,"min":5,"fgm":4,"fga":4,"fgp":12,"ftm":11,"fta":5,"ftp":13,"tpm":3,"tpa":3,"tpp":7,"offReb":5,"defReb":6,"totReb":5,"assists":2,"pFouls":11,"steals":18,"turnovers":1,"blocks":6,"plusMinus":5}},{"personId":"203076","firstName":"Anthony","lastName":"Davis","jersey":"3","teamId":"1610612747","isOnCourt":true,"points":"37","pos":"PF","position_full":"Power Forward","player_code":"anthony_davis","min":"38:46","fgm":"14","fga":"22","fgp":"63.6","ftm":"6","fta":"8","ftp":"75.0","tpm":"3","tpa":"5","tpp":"60.0","offReb":"3","defReb":"12","totReb":"15","assists":"6","pFouls":"1","steals":"1","turnovers":"3","blocks":"5","plusMinus":"-13","dnp":"","sortKey":{"name":42,"pos":0,"points":2,"min":4,"fgm":2,"fga":2,"fgp":5,"ftm":2,"fta":1,"ftp":5,"tpm":2,"tpa":5,"tpp":3,"offReb":2,"defReb":1,"totReb":1,"assists":3,"pFouls":14,"steals":4,"turnovers":3,"blocks":1,"plusMinus":23}},{"personId":"201580","firstName":"JaVale","lastName":"McGee","jersey":"7","teamId":"1610612747","isOnCourt":false,"points":"6","pos":"C","position_full":"Center","player_code":"javale_mcgee","min":"14:23","fgm":"3","fga":"4","fgp":"75.0","ftm":"0","fta":"0","ftp":"0.0","tpm":"0","tpa":"0","tpp":"0.0","offReb":"1","defReb":"2","totReb":"3","assists":"0","pFouls":"1","steals":"0","turnovers":"1","blocks":"2","plusMinus":"-2","dnp":"","sortKey":{"name":43,"pos":0,"points":12,"min":13,"fgm":10,"fga":13,"fgp":4,"ftm":19,"fta":19,"ftp":19,"tpm":18,"tpa":24,"tpp":18,"offReb":11,"defReb":13,"totReb":13,"assists":20,"pFouls":18,"steals":16,"turnovers":9,"blocks":3,"plusMinus":16}},{"personId":"201980","firstName":"Danny","lastName":"Green","jersey":"14","teamId":"1610612747","isOnCourt":false,"points":"5","pos":"SG","position_full":"Shooting Guard","player_code":"danny_green","min":"21:47","fgm":"1","fga":"8","fgp":"12.5","ftm":"2","fta":"3","ftp":"66.7","tpm":"1","tpa":"6","tpp":"16.7","offReb":"1","defReb":"2","totReb":"3","assists":"1","pFouls":"1","steals":"0","turnovers":"0","blocks":"1","plusMinus":"1","dnp":"","sortKey":{"name":44,"pos":0,"points":14,"min":10,"fgm":15,"fga":8,"fgp":19,"ftm":7,"fta":6,"ftp":7,"tpm":8,"tpa":4,"tpp":10,"offReb":9,"defReb":12,"totReb":11,"assists":12,"pFouls":16,"steals":12,"turnovers":16,"blocks":4,"plusMinus":12}},{"personId":"202340","firstName":"Avery","lastName":"Bradley","jersey":"11","teamId":"1610612747","isOnCourt":true,"points":"10","pos":"PG","position_full":"Point Guard","player_code":"avery_bradley","min":"25:25","fgm":"3","fga":"6","fgp":"50.0","ftm":"2","fta":"2","ftp":"100","tpm":"2","tpa":"3","tpp":"66.7","offReb":"1","defReb":"4","totReb":"5","assists":"2","pFouls":"2","steals":"0","turnovers":"0","blocks":"0","plusMinus":"-5","dnp":"","sortKey":{"name":45,"pos":0,"points":7,"min":7,"fgm":8,"fga":10,"fgp":8,"ftm":6,"fta":8,"ftp":2,"tpm":4,"tpa":8,"tpp":2,"offReb":6,"defReb":8,"totReb":8,"assists":9,"pFouls":7,"steals":8,"turnovers":13,"blocks":12,"plusMinus":18}},{"personId":"1628398","firstName":"Kyle","lastName":"Kuzma","jersey":"0","teamId":"1610612747","isOnCourt":true,"points":"17","pos":"","position_full":"","player_code":"kyle_kuzma","min":"25:04","fgm":"6","fga":"12","fgp":"50.0","ftm":"5","fta":"7","ftp":"71.4","tpm":"0","tpa":"3","tpp":"0.0","offReb":"5","defReb":"10","totReb":"15","assists":"0","pFouls":"2","steals":"0","turnovers":"4","blocks":"0","plusMinus":"-16","dnp":"","sortKey":{"name":46,"pos":0,"points":6,"min":8,"fgm":6,"fga":6,"fgp":9,"ftm":3,"fta":3,"ftp":6,"tpm":19,"tpa":10,"tpp":19,"offReb":1,"defReb":3,"totReb":2,"assists":21,"pFouls":10,"steals":17,"turnovers":2,"blocks":20,"plusMinus":24}},{"personId":"203484","firstName":"Kentavious","lastName":"Caldwell-Pope","jersey":"1","teamId":"1610612747","isOnCourt":true,"points":"8","pos":"","position_full":"","player_code":"kentavious_caldwell-pope","min":"21:11","fgm":"3","fga":"7","fgp":"42.9","ftm":"1","fta":"2","ftp":"50.0","tpm":"1","tpa":"3","tpp":"33.3","offReb":"1","defReb":"0","totReb":"1","assists":"1","pFouls":"2","steals":"1","turnovers":"0","blocks":"0","plusMinus":"-10","dnp":"","sortKey":{"name":47,"pos":0,"points":9,"min":11,"fgm":11,"fga":9,"fgp":11,"ftm":10,"fta":10,"ftp":10,"tpm":9,"tpa":9,"tpp":8,"offReb":12,"defReb":19,"totReb":17,"assists":14,"pFouls":9,"steals":5,"turnovers":19,"blocks":19,"plusMinus":21}},{"personId":"203584","firstName":"Troy","lastName":"Daniels","jersey":"30","teamId":"1610612747","isOnCourt":false,"points":"3","pos":"","position_full":"","player_code":"troy_daniels","min":"7:45","fgm":"1","fga":"4","fgp":"25.0","ftm":"1","fta":"2","ftp":"50.0","tpm":"0","tpa":"1","tpp":"0.0","offReb":"3","defReb":"0","totReb":"3","assists":"1","pFouls":"2","steals":"0","turnovers":"1","blocks":"0","plusMinus":"-2","dnp":"","sortKey":{"name":48,"pos":0,"points":17,"min":21,"fgm":19,"fga":15,"fgp":17,"ftm":13,"fta":12,"ftp":12,"tpm":23,"tpa":17,"tpp":23,"offReb":4,"defReb":23,"totReb":14,"assists":15,"pFouls":13,"steals":23,"turnovers":10,"blocks":24,"plusMinus":17}},{"personId":"200765","firstName":"Rajon","lastName":"Rondo","jersey":"9","teamId":"1610612747","isOnCourt":false,"points":"2","pos":"","position_full":"","player_code":"rajon_rondo","min":"14:13","fgm":"1","fga":"3","fgp":"33.3","ftm":"0","fta":"0","ftp":"0.0","tpm":"0","tpa":"1","tpp":"0.0","offReb":"0","defReb":"0","totReb":"0","assists":"5","pFouls":"0","steals":"0","turnovers":"2","blocks":"0","plusMinus":"-11","dnp":"","sortKey":{"name":49,"pos":0,"points":18,"min":15,"fgm":17,"fga":19,"fgp":16,"ftm":22,"fta":22,"ftp":22,"tpm":21,"tpa":16,"tpp":21,"offReb":23,"defReb":22,"totReb":24,"assists":5,"pFouls":24,"steals":22,"turnovers":5,"blocks":23,"plusMinus":22}},{"personId":"201162","firstName":"Jared","lastName":"Dudley","jersey":"10","teamId":"1610612747","isOnCourt":false,"points":"0","pos":"","position_full":"","player_code":"jared_dudley","min":"5:53","fgm":"0","fga":"0","fgp":"0.0","ftm":"0","fta":"0","ftp":"0.0","tpm":"0","tpa":"0","tpp":"0.0","offReb":"0","defReb":"3","totReb":"3","assists":"0","pFouls":"0","steals":"0","turnovers":"0","blocks":"0","plusMinus":"6","dnp":"","sortKey":{"name":50,"pos":0,"points":23,"min":22,"fgm":22,"fga":24,"fgp":22,"ftm":18,"fta":18,"ftp":18,"tpm":17,"tpa":23,"tpp":17,"offReb":19,"defReb":11,"totReb":12,"assists":19,"pFouls":22,"steals":15,"turnovers":18,"blocks":18,"plusMinus":7}},{"personId":"2730","firstName":"Dwight","lastName":"Howard","jersey":"39","teamId":"1610612747","isOnCourt":false,"points":"6","pos":"","position_full":"","player_code":"dwight_howard","min":"14:14","fgm":"3","fga":"3","fgp":"100","ftm":"0","fta":"0","ftp":"0.0","tpm":"0","tpa":"0","tpp":"0.0","offReb":"1","defReb":"3","totReb":"4","assists":"0","pFouls":"5","steals":"0","turnovers":"1","blocks":"1","plusMinus":"6","dnp":"","sortKey":{"name":51,"pos":0,"points":11,"min":14,"fgm":9,"fga":17,"fgp":2,"ftm":16,"fta":16,"ftp":16,"tpm":15,"tpa":21,"tpp":15,"offReb":10,"defReb":10,"totReb":9,"assists":18,"pFouls":2,"steals":13,"turnovers":7,"blocks":5,"plusMinus":6}},{"personId":"1627936","firstName":"Alex","lastName":"Caruso","jersey":"4","teamId":"1610612747","isOnCourt":false,"points":"0","pos":"","position_full":"","player_code":"alex_caruso","min":"8:17","fgm":"0","fga":"2","fgp":"0.0","ftm":"0","fta":"0","ftp":"0.0","tpm":"0","tpa":"1","tpp":"0.0","offReb":"0","defReb":"1","totReb":"1","assists":"2","pFouls":"3","steals":"0","turnovers":"0","blocks":"0","plusMinus":"-2","dnp":"","sortKey":{"name":52,"pos":0,"points":21,"min":20,"fgm":20,"fga":21,"fgp":20,"ftm":14,"fta":14,"ftp":14,"tpm":11,"tpa":13,"tpp":11,"offReb":14,"defReb":15,"totReb":16,"assists":7,"pFouls":4,"steals":6,"turnovers":11,"blocks":10,"plusMinus":15}},{"personId":"1626188","firstName":"Quinn","lastName":"Cook","jersey":"28","teamId":"1610612747","isOnCourt":false,"points":"3","pos":"","position_full":"","player_code":"quinn_cook","min":"5:02","fgm":"1","fga":"3","fgp":"33.3","ftm":"0","fta":"0","ftp":"0.0","tpm":"1","tpa":"1","tpp":"100","offReb":"0","defReb":"0","totReb":"0","assists":"0","pFouls":"0","steals":"0","turnovers":"0","blocks":"0","plusMinus":"1","dnp":"","sortKey":{"name":53,"pos":0,"points":16,"min":23,"fgm":16,"fga":18,"fgp":15,"ftm":21,"fta":21,"ftp":21,"tpm":10,"tpa":15,"tpp":1,"offReb":22,"defReb":21,"totReb":23,"assists":24,"pFouls":23,"steals":21,"turnovers":22,"blocks":22,"plusMinus":13}}]}}